hashdial/__init__.py
hashdial-1.0.3.dist-info/LICENSE
hashdial-1.0.3.dist-info/LICENSE.txt
hashdial-1.0.3.dist-info/METADATA
hashdial-1.0.3.dist-info/WHEEL
hashdial-1.0.3.dist-info/top_level.txt
hashdial-1.0.3.dist-info/RECORD
