Metadata-Version: 2.1
Name: hashdial
Version: 1.0.3
Summary: A module implementing hash based decision making
Home-page: https://github.com/scode/py-hashdial
Author: Peter Schuller
Author-email: peter.schuller@infidyne.com
License: UNKNOWN
Project-URL: Documentation, http://py-hashdial.readthedocs.io/en/latest/
Project-URL: Source, https://github.com/scode/py-hashdial
Keywords: hashdial hashing decision
Platform: UNKNOWN
Classifier: Development Status :: 5 - Production/Stable
Classifier: Intended Audience :: Developers
Classifier: Topic :: Software Development :: Libraries
Classifier: License :: OSI Approved :: MIT License
Classifier: Programming Language :: Python :: 3
Classifier: Programming Language :: Python :: 3.4
Classifier: Programming Language :: Python :: 3.5
Classifier: Programming Language :: Python :: 3.6
Requires-Python: >3.4
Requires-Dist: typing ; python_version < "3.5"
